README.md
setup.py
anduin/Scheduler.py
anduin/__init__.py
anduin/construct_file.py
anduin.egg-info/PKG-INFO
anduin.egg-info/SOURCES.txt
anduin.egg-info/dependency_links.txt
anduin.egg-info/requires.txt
anduin.egg-info/top_level.txt
anduin.egg-info/zip-safe
anduin/common/__init__.py
anduin/common/tools.py
anduin/db/__init__.py
anduin/db/no_sql/__init__.py
anduin/db/no_sql/async_redis/__init__.py
anduin/db/no_sql/async_redis/redis_client.py
anduin/db/no_sql/async_redis/redis_client_manager.py
anduin/db/no_sql/redis/__init__.py
anduin/db/no_sql/redis/redis_client.py
anduin/db/no_sql/redis/redis_client_manager.py
anduin/db/sql/__init__.py
anduin/db/sql/async_mysql/__init__.py
anduin/db/sql/async_mysql/db_client.py
anduin/db/sql/async_mysql/db_client_manager.py
anduin/db/sql/clickhouse/__init__.py
anduin/db/sql/clickhouse/db_client.py
anduin/db/sql/clickhouse/db_client_manager.py
anduin/db/sql/mysql/__init__.py
anduin/db/sql/mysql/db_client.py
anduin/db/sql/mysql/db_client_manager.py
anduin/db/sql/sqlite/__init__.py
anduin/db/sql/sqlite/db_client.py
anduin/db/sql/sqlite/db_client_manager.py
anduin/frames/__init__.py
anduin/frames/client_base.py
anduin/frames/manager_base.py
anduin/parser/__init__.py
anduin/parser/sql_parser.py
test/__init__.py
test/testbyte.py